{"cs_net_css_pre.md":"Dhi33TcT","cs_net_docker_command.md":"CMgdaS88","cs_net_http_cache.md":"CJPgVUar","cs_net_http_version.md":"CVOq7piU","cs_net_https.md":"DIfOgcTP","cs_net_jwt.md":"DHQKH3LM","cs_net_keep_alive.md":"EhfNmcF5","cs_net_nginx.md":"C731ztxo","cs_net_osi.md":"CxotU__r","cs_net_pnpm.md":"D820uWyB","cs_net_statecode.md":"7VfZZ9N_","dm_pu_ob.md":"BAGEycyZ","dm_strategy.md":"DhKt9N9x","fe_css_css.md":"BiU80afw","fe_css_flex.md":"DqNU9XuK","fe_css_grid.md":"BskiJK8-","fe_css_less.md":"9UgFSwSD","fe_git_git.md":"DmFOB5CI","fe_html_html.md":"CpicocEZ","fe_ide_vscode.md":"CcvL3ZpA","fe_js_array.md":"D6UUD4z0","fe_js_coding_problem.md":"ClDkPLJX","fe_js_js_modules.md":"Vjp0xhHt","fe_js_webstorage.md":"D1-Hi60c","fe_js_what_is_js.md":"DWWGGMXU","fe_microfrontends_microfrontends.md":"DwvMuweG","fe_microfrontends_monorepo.md":"DdjGz3-E","fe_microfrontends_raf_rsc.md":"CdvinpCE","fe_microfrontends_wujie.md":"Do70BpvB","fe_request_jwt.md":"DmFjyMYX","fe_uniapp_jwt.md":"BSw6AiQ3","fe_vue_vue3.md":"C3TiyDbW","fe_vue_vue_cli.md":"DSRqtOd1","fe_vue_vue_component_advanced.md":"Cc8bk_Ks","fe_vue_vue_component_coding.md":"C3hj9g86","fe_vue_vue_core_basis.md":"BguW0Xg7","fe_vue_vue_network_request.md":"CYYnmQES","fe_vue_vue_router.md":"LDkXWy8F","fe_vue_vuex.md":"B92vCwh8","fe_vuepress_vitepress.md":"DU_wCtG_","fe_vuepress_vuepress.md":"BaYzV6fB","fe_webpack_webpack_basis.md":"qkVAEQOb","index.md":"Sbpq02EB","other_java_copy.md":"BH0LbhrV","other_java_hashmap.md":"Bd0YqeZZ","other_java_static.md":"0Rk6RvGQ","other_java_this.md":"Bg1ljG9x","other_nodejs_ev_api_server.md":"Dk33vmii","other_nodejs_express.md":"xWabYpDO","other_nodejs_mysql.md":"B__0VcwL","other_nodejs_node_basis.md":"BmSzbUBF","projects_chess_project_index.md":"C1c0x8DN","projects_dxyy_project_index.md":"XNklEB7K","projects_ggdt_project_index.md":"CCR8Yzkm","resources_navigation_nav.md":"BltUb62m","resources_website_fe_blogs.md":"BjI6G90t","resources_website_other_blogs.md":"BkYu_9iB","timeline_index.md":"BUVaYs57","timeline_issue-10.md":"k3ndxY8m","timeline_issue-11.md":"DLlherEA","timeline_issue-12.md":"BEmWyyvq","timeline_issue-13.md":"DIA9Qmjz","timeline_issue-14.md":"H5kmS1iZ","timeline_issue-15.md":"DHsZCtjC","timeline_issue-16.md":"BXfjj_WI","timeline_issue-17.md":"aT_Cvsfq","timeline_issue-18.md":"FFUAj7Po","timeline_issue-19.md":"B7LJG3cs","timeline_issue-20.md":"C9Y6iEVk","timeline_issue-21.md":"DDaZW-f-","timeline_issue-22.md":"Dv_GLqAu","timeline_issue-23.md":"BFsKEgxw","timeline_issue-24.md":"CgK4KK4-","timeline_issue-25.md":"CPIgS2c_","timeline_issue-26.md":"CYbwwC0N","timeline_issue-27.md":"DOjahANq","timeline_issue-28.md":"Bq1RkUmA","timeline_issue-29.md":"CIWbw1YG","timeline_issue-30.md":"Buy2aF1E","timeline_issue-31.md":"DpvDJV5l","timeline_issue-32.md":"gmABGPgG","timeline_issue-33.md":"BEy2whQC","timeline_issue-34.md":"Dcaehjiw","timeline_issue-35.md":"Bc9taD-X","timeline_issue-36.md":"DKorEaUC","timeline_issue-37.md":"C2gMX58X","timeline_issue-38.md":"BrP5MZ8S","timeline_issue-39.md":"7tszzK2v","timeline_issue-40.md":"BpCRZaBO","timeline_issue-41.md":"CWtEj0vt","timeline_issue-42.md":"DwKWrRr2","timeline_issue-43.md":"BCE4ju7b","timeline_issue-44.md":"CfnmLSJl","timeline_issue-45.md":"DazTqcHh","timeline_issue-46.md":"Cuqt0HnJ","timeline_issue-47.md":"BZbapzmq","timeline_issue-48.md":"D0dTL2V5","timeline_issue-49.md":"C-Hw8pL0","timeline_issue-5.md":"DVdDTH4D","timeline_issue-50.md":"BeDgqmqp","timeline_issue-51.md":"BEPmo9uE","timeline_issue-52.md":"H4Gu-RBS","timeline_issue-53.md":"C_njwjPV","timeline_issue-54.md":"Dwmgmt6R","timeline_issue-55.md":"BYNR2hqo","timeline_issue-56.md":"DuQ9uHYk","timeline_issue-57.md":"DT-w8dLV","timeline_issue-6.md":"BftGwMT4","timeline_issue-60.md":"Bsf6fCH4","timeline_issue-61.md":"Dx6rW3MS","timeline_issue-62.md":"SSkQVegf","timeline_issue-64.md":"Ddl8NAx0","timeline_issue-65.md":"BLI-SC1y","timeline_issue-66.md":"DCISlMhe","timeline_issue-67.md":"DbNGrtLV","timeline_issue-68.md":"CsCTWm0T","timeline_issue-69.md":"C83fT2AH","timeline_issue-7.md":"8PCZ3dGn","timeline_issue-70.md":"q8MWAPet","timeline_issue-71.md":"BmPVetAA","timeline_issue-72.md":"Bbro6gQk","timeline_issue-74.md":"C0Q69_fV","timeline_issue-75.md":"DpAJdSbx","timeline_issue-76.md":"Njx70sAY","timeline_issue-77.md":"DYnUn1ra","timeline_issue-78.md":"DcoUjTNm","timeline_issue-79.md":"D25A6hw5","timeline_issue-8.md":"CHXscMvq","timeline_issue-81.md":"Db1exvZr","timeline_issue-82.md":"BGhQ1LNt","timeline_issue-9.md":"tHyF6g1P"}
