{"cs_net_css_pre.md":"2CC3Gtxo","cs_net_docker_command.md":"DKUnWA9h","cs_net_http_cache.md":"D9G_WFRZ","cs_net_http_version.md":"gK2oWIYY","cs_net_https.md":"CYIrKADD","cs_net_jwt.md":"CwCfKJjU","cs_net_keep_alive.md":"CHyTL5E9","cs_net_nginx.md":"CaAkvwpR","cs_net_osi.md":"Cabwffv5","cs_net_pnpm.md":"CDmmLTaK","cs_net_statecode.md":"BYKVLWGd","dm_pu_ob.md":"CbHIuTqY","dm_strategy.md":"D12NU0SQ","fe_css_css.md":"BscYdoTW","fe_css_flex.md":"DhJi2Rvj","fe_css_grid.md":"DJAV-eNI","fe_css_less.md":"BGTldAJo","fe_git_git.md":"CnUyjWbw","fe_html_html.md":"C3pIj6j8","fe_ide_vscode.md":"DOYvkrwT","fe_js_array.md":"CvCNxu-k","fe_js_coding_problem.md":"IlMDU37O","fe_js_js_modules.md":"BVCWAzjL","fe_js_webstorage.md":"Cm16VlHX","fe_js_what_is_js.md":"iww47Dhb","fe_microfrontends_microfrontends.md":"BkPV7iwD","fe_microfrontends_monorepo.md":"JyCP9tAB","fe_microfrontends_raf_rsc.md":"CiiGFeo0","fe_microfrontends_wujie.md":"CJ8nsDIX","fe_request_jwt.md":"XR5OY0no","fe_uniapp_jwt.md":"DNfjgNN1","fe_vue_vue3.md":"C3p4r99l","fe_vue_vue_cli.md":"zdL7Zpi3","fe_vue_vue_component_advanced.md":"CQql3CNm","fe_vue_vue_component_coding.md":"7fF1Mcwn","fe_vue_vue_core_basis.md":"BIcgJ2xA","fe_vue_vue_network_request.md":"DLyyry-i","fe_vue_vue_router.md":"D3mFpV-F","fe_vue_vuex.md":"B8CbCv9T","fe_vuepress_vitepress.md":"DpWpLD5E","fe_vuepress_vuepress.md":"sy3_d8WD","fe_webpack_webpack_basis.md":"Dd3DpoJr","index.md":"BOWUl5Mt","other_java_copy.md":"CvHnEf40","other_java_hashmap.md":"DGc55C5f","other_java_static.md":"Bf7UsUcy","other_java_this.md":"Bk-Fe-NG","other_nodejs_ev_api_server.md":"CwmOV2Wm","other_nodejs_express.md":"DHOkrMkZ","other_nodejs_mysql.md":"CYx3iH76","other_nodejs_node_basis.md":"PRXtm3M-","projects_chess_project_index.md":"BRh9EzED","projects_dxyy_project_index.md":"BhGZ-2vM","projects_ggdt_project_index.md":"B2aZv-Lm","resources_navigation_nav.md":"DAI7BLlG","resources_website_fe_blogs.md":"Ck0A1xAj","resources_website_other_blogs.md":"CufcUU1j","timeline_index.md":"B_wx1tmz","timeline_issue-10.md":"CzwSOSRI","timeline_issue-11.md":"DBwRlV_k","timeline_issue-12.md":"CW7ZlX4J","timeline_issue-13.md":"9OYI9kyy","timeline_issue-14.md":"CtIuKDL6","timeline_issue-15.md":"2eyaiZp0","timeline_issue-16.md":"D3DodjDt","timeline_issue-17.md":"D1V-X15r","timeline_issue-18.md":"QJxG3g6d","timeline_issue-19.md":"DWiuyKA1","timeline_issue-20.md":"ehFVdfxc","timeline_issue-21.md":"BjR1cd6-","timeline_issue-22.md":"stps7WH-","timeline_issue-23.md":"DH3Y7ctV","timeline_issue-24.md":"DRbD-1Re","timeline_issue-25.md":"K2yzH-Oh","timeline_issue-26.md":"CVubQlDv","timeline_issue-27.md":"BUvl6iL7","timeline_issue-28.md":"BPWgOeqD","timeline_issue-29.md":"D0w4lhtj","timeline_issue-30.md":"BrvfSYR-","timeline_issue-31.md":"ClL6w32u","timeline_issue-32.md":"C8SmjtDx","timeline_issue-33.md":"BDa3dYUQ","timeline_issue-34.md":"DoRGOWDJ","timeline_issue-35.md":"UOEL-8iW","timeline_issue-36.md":"BIedzYLm","timeline_issue-37.md":"CZtguwwN","timeline_issue-38.md":"COJ9z2fh","timeline_issue-39.md":"DA8RyEnv","timeline_issue-40.md":"DiHaSMt8","timeline_issue-41.md":"DSwgYCEE","timeline_issue-42.md":"DTSHBjdF","timeline_issue-43.md":"BliyQDuE","timeline_issue-44.md":"Ddj-N0uZ","timeline_issue-45.md":"DHPkknNx","timeline_issue-46.md":"CpjTJYX5","timeline_issue-47.md":"Bzj20GjV","timeline_issue-48.md":"252qIFFX","timeline_issue-49.md":"BRa-_dDF","timeline_issue-5.md":"Ch5kEGV_","timeline_issue-50.md":"B3wRVzMg","timeline_issue-51.md":"Cs8hpcBF","timeline_issue-52.md":"DwI44XQP","timeline_issue-53.md":"T8uDH9fU","timeline_issue-54.md":"2c_worgr","timeline_issue-55.md":"CYrLvhSQ","timeline_issue-56.md":"2DdWjWqp","timeline_issue-57.md":"JizlQMgJ","timeline_issue-6.md":"BJxBtjnu","timeline_issue-60.md":"Z1nzRkg3","timeline_issue-61.md":"BWnpKThH","timeline_issue-62.md":"Dnl8sWy-","timeline_issue-64.md":"C94cTHvX","timeline_issue-65.md":"ClGes6SN","timeline_issue-66.md":"CUptyLEI","timeline_issue-67.md":"DPJNRgsI","timeline_issue-68.md":"sONiETuU","timeline_issue-69.md":"eQHy4cZ9","timeline_issue-7.md":"aOy7YNUh","timeline_issue-70.md":"DULWNAgk","timeline_issue-71.md":"B2g3UMpW","timeline_issue-72.md":"CDb1psyP","timeline_issue-74.md":"DfdnLPxe","timeline_issue-75.md":"BqNgue1X","timeline_issue-76.md":"BLjBFriY","timeline_issue-77.md":"DOSuuPB1","timeline_issue-78.md":"Btcip1EO","timeline_issue-79.md":"ChyGj0_N","timeline_issue-8.md":"L7KfFFOH","timeline_issue-81.md":"BohyUcYz","timeline_issue-82.md":"BJtN17Uo","timeline_issue-83.md":"C6iGwBy3","timeline_issue-84.md":"BDghPfYk","timeline_issue-85.md":"yP_7Iu6Y","timeline_issue-86.md":"CCktoQNB","timeline_issue-87.md":"yWi5RM_i","timeline_issue-88.md":"Bl2tlQws","timeline_issue-9.md":"C1ERyV18"}
